{
  "strategy": "top3pct_2020_2022",
  "snapshot_id": "67f102cf7d359388",
  "snapshot_manifest": {
    "universe_label": "sp500_pit",
    "universe_as_of": "2020-05-13",
    "window_start": "2020-05-13",
    "window_end": "2022-05-13",
    "n_tickers_with_prices": 473
  },
  "parameters": {
    "top_decile": 0.03,
    "rebalance_days": 63,
    "cost_bps": 5.0,
    "starting_cash": 10000.0,
    "regime_filter_enabled": true
  },
  "metrics": {
    "total_return_pct": -3.99,
    "cagr_pct": -4.04,
    "ann_sharpe": -0.417,
    "max_drawdown_pct": -8.1,
    "n_trades": 26,
    "n_rebalances": 1,
    "n_risk_off_periods": 3,
    "final_equity": 9601.45
  },
  "benchmark_spy": {
    "total_return_pct": -4.34,
    "ann_sharpe": -0.176,
    "max_drawdown_pct": -17.62
  },
  "alpha_vs_spy_pct": 0.35,
  "walk_forward": {
    "folds": [
      {
        "fold": 0,
        "sharpe": 0.0,
        "return_pct": 0.0,
        "n_days": 50
      },
      {
        "fold": 1,
        "sharpe": 0.0,
        "return_pct": 0.0,
        "n_days": 50
      },
      {
        "fold": 2,
        "sharpe": -1.317,
        "return_pct": -3.52,
        "n_days": 50
      },
      {
        "fold": 3,
        "sharpe": -0.09,
        "return_pct": -0.49,
        "n_days": 50
      },
      {
        "fold": 4,
        "sharpe": 0.0,
        "return_pct": 0.0,
        "n_days": 50
      }
    ],
    "mean_sharpe": -0.281,
    "min_sharpe": -1.317,
    "passed": false
  },
  "trades_sample": [
    {
      "date": "2021-11-12",
      "ticker": "ZION",
      "side": "buy",
      "shares": 12,
      "price": 55.7847,
      "cost": 0.3347
    },
    {
      "date": "2021-11-12",
      "ticker": "GOOGL",
      "side": "buy",
      "shares": 4,
      "price": 147.4592,
      "cost": 0.2949
    },
    {
      "date": "2021-11-12",
      "ticker": "NVDA",
      "side": "buy",
      "shares": 23,
      "price": 30.3259,
      "cost": 0.3487
    },
    {
      "date": "2021-11-12",
      "ticker": "AVGO",
      "side": "buy",
      "shares": 13,
      "price": 51.7321,
      "cost": 0.3363
    },
    {
      "date": "2021-11-12",
      "ticker": "CPRT",
      "side": "buy",
      "shares": 18,
      "price": 38.9125,
      "cost": 0.3502
    },
    {
      "date": "2021-11-12",
      "ticker": "BKNG",
      "side": "buy",
      "shares": 7,
      "price": 96.2676,
      "cost": 0.3369
    },
    {
      "date": "2021-11-12",
      "ticker": "COO",
      "side": "buy",
      "shares": 6,
      "price": 104.3949,
      "cost": 0.3132
    },
    {
      "date": "2021-11-12",
      "ticker": "C",
      "side": "buy",
      "shares": 12,
      "price": 59.0285,
      "cost": 0.3542
    },
    {
      "date": "2021-11-12",
      "ticker": "REGN",
      "side": "buy",
      "shares": 1,
      "price": 626.9645,
      "cost": 0.3135
    },
    {
      "date": "2021-11-12",
      "ticker": "COF",
      "side": "buy",
      "shares": 4,
      "price": 145.2651,
      "cost": 0.2905
    },
    {
      "date": "2021-11-12",
      "ticker": "SLG",
      "side": "buy",
      "shares": 12,
      "price": 55.9094,
      "cost": 0.3355
    },
    {
      "date": "2021-11-12",
      "ticker": "GILD",
      "side": "buy",
      "shares": 12,
      "price": 57.1636,
      "cost": 0.343
    },
    {
      "date": "2021-11-12",
      "ticker": "GOOG",
      "side": "buy",
      "shares": 4,
      "price": 148.4269,
      "cost": 0.2969
    },
    {
      "date": "2022-02-14",
      "ticker": "ZION",
      "side": "sell_regime_off",
      "shares": 12,
      "price": 61.646,
      "cost": 0.3699
    },
    {
      "date": "2022-02-14",
      "ticker": "GOOGL",
      "side": "sell_regime_off",
      "shares": 4,
      "price": 134.4151,
      "cost": 0.2688
    },
    {
      "date": "2022-02-14",
      "ticker": "NVDA",
      "side": "sell_regime_off",
      "shares": 23,
      "price": 24.2188,
      "cost": 0.2785
    },
    {
      "date": "2022-02-14",
      "ticker": "AVGO",
      "side": "sell_regime_off",
      "shares": 13,
      "price": 53.4829,
      "cost": 0.3476
    },
    {
      "date": "2022-02-14",
      "ticker": "CPRT",
      "side": "sell_regime_off",
      "shares": 18,
      "price": 30.6825,
      "cost": 0.2761
    },
    {
      "date": "2022-02-14",
      "ticker": "BKNG",
      "side": "sell_regime_off",
      "shares": 7,
      "price": 99.9591,
      "cost": 0.3499
    },
    {
      "date": "2022-02-14",
      "ticker": "COO",
      "side": "sell_regime_off",
      "shares": 6,
      "price": 97.812,
      "cost": 0.2934
    },
    {
      "date": "2022-02-14",
      "ticker": "C",
      "side": "sell_regime_off",
      "shares": 12,
      "price": 57.1708,
      "cost": 0.343
    },
    {
      "date": "2022-02-14",
      "ticker": "REGN",
      "side": "sell_regime_off",
      "shares": 1,
      "price": 619.3459,
      "cost": 0.3097
    },
    {
      "date": "2022-02-14",
      "ticker": "COF",
      "side": "sell_regime_off",
      "shares": 4,
      "price": 144.2768,
      "cost": 0.2886
    },
    {
      "date": "2022-02-14",
      "ticker": "SLG",
      "side": "sell_regime_off",
      "shares": 12,
      "price": 57.6022,
      "cost": 0.3456
    },
    {
      "date": "2022-02-14",
      "ticker": "GILD",
      "side": "sell_regime_off",
      "shares": 12,
      "price": 52.2932,
      "cost": 0.3138
    },
    {
      "date": "2022-02-14",
      "ticker": "GOOG",
      "side": "sell_regime_off",
      "shares": 4,
      "price": 134.1982,
      "cost": 0.2684
    }
  ],
  "rebalance_log": [
    {
      "date": "2021-05-17",
      "action": "risk_off",
      "n_positions": 0
    },
    {
      "date": "2021-08-16",
      "action": "risk_off",
      "n_positions": 0
    },
    {
      "date": "2021-11-12",
      "action": "rebalance",
      "n_positions": 13,
      "n_long": 13,
      "n_short": 0,
      "regime": "low_vix"
    },
    {
      "date": "2022-02-14",
      "action": "risk_off",
      "n_positions": 0
    }
  ],
  "equity_curve": [
    [
      "2021-05-17",
      10000.0
    ],
    [
      "2021-05-18",
      10000.0
    ],
    [
      "2021-05-19",
      10000.0
    ],
    [
      "2021-05-20",
      10000.0
    ],
    [
      "2021-05-21",
      10000.0
    ],
    [
      "2021-05-24",
      10000.0
    ],
    [
      "2021-05-25",
      10000.0
    ],
    [
      "2021-05-26",
      10000.0
    ],
    [
      "2021-05-27",
      10000.0
    ],
    [
      "2021-05-28",
      10000.0
    ],
    [
      "2021-06-01",
      10000.0
    ],
    [
      "2021-06-02",
      10000.0
    ],
    [
      "2021-06-03",
      10000.0
    ],
    [
      "2021-06-04",
      10000.0
    ],
    [
      "2021-06-07",
      10000.0
    ],
    [
      "2021-06-08",
      10000.0
    ],
    [
      "2021-06-09",
      10000.0
    ],
    [
      "2021-06-10",
      10000.0
    ],
    [
      "2021-06-11",
      10000.0
    ],
    [
      "2021-06-14",
      10000.0
    ],
    [
      "2021-06-15",
      10000.0
    ],
    [
      "2021-06-16",
      10000.0
    ],
    [
      "2021-06-17",
      10000.0
    ],
    [
      "2021-06-18",
      10000.0
    ],
    [
      "2021-06-21",
      10000.0
    ],
    [
      "2021-06-22",
      10000.0
    ],
    [
      "2021-06-23",
      10000.0
    ],
    [
      "2021-06-24",
      10000.0
    ],
    [
      "2021-06-25",
      10000.0
    ],
    [
      "2021-06-28",
      10000.0
    ],
    [
      "2021-06-29",
      10000.0
    ],
    [
      "2021-06-30",
      10000.0
    ],
    [
      "2021-07-01",
      10000.0
    ],
    [
      "2021-07-02",
      10000.0
    ],
    [
      "2021-07-06",
      10000.0
    ],
    [
      "2021-07-07",
      10000.0
    ],
    [
      "2021-07-08",
      10000.0
    ],
    [
      "2021-07-09",
      10000.0
    ],
    [
      "2021-07-12",
      10000.0
    ],
    [
      "2021-07-13",
      10000.0
    ],
    [
      "2021-07-14",
      10000.0
    ],
    [
      "2021-07-15",
      10000.0
    ],
    [
      "2021-07-16",
      10000.0
    ],
    [
      "2021-07-19",
      10000.0
    ],
    [
      "2021-07-20",
      10000.0
    ],
    [
      "2021-07-21",
      10000.0
    ],
    [
      "2021-07-22",
      10000.0
    ],
    [
      "2021-07-23",
      10000.0
    ],
    [
      "2021-07-26",
      10000.0
    ],
    [
      "2021-07-27",
      10000.0
    ],
    [
      "2021-07-28",
      10000.0
    ],
    [
      "2021-07-29",
      10000.0
    ],
    [
      "2021-07-30",
      10000.0
    ],
    [
      "2021-08-02",
      10000.0
    ],
    [
      "2021-08-03",
      10000.0
    ],
    [
      "2021-08-04",
      10000.0
    ],
    [
      "2021-08-05",
      10000.0
    ],
    [
      "2021-08-06",
      10000.0
    ],
    [
      "2021-08-09",
      10000.0
    ],
    [
      "2021-08-10",
      10000.0
    ],
    [
      "2021-08-11",
      10000.0
    ],
    [
      "2021-08-12",
      10000.0
    ],
    [
      "2021-08-13",
      10000.0
    ],
    [
      "2021-08-16",
      10000.0
    ],
    [
      "2021-08-17",
      10000.0
    ],
    [
      "2021-08-18",
      10000.0
    ],
    [
      "2021-08-19",
      10000.0
    ],
    [
      "2021-08-20",
      10000.0
    ],
    [
      "2021-08-23",
      10000.0
    ],
    [
      "2021-08-24",
      10000.0
    ],
    [
      "2021-08-25",
      10000.0
    ],
    [
      "2021-08-26",
      10000.0
    ],
    [
      "2021-08-27",
      10000.0
    ],
    [
      "2021-08-30",
      10000.0
    ],
    [
      "2021-08-31",
      10000.0
    ],
    [
      "2021-09-01",
      10000.0
    ],
    [
      "2021-09-02",
      10000.0
    ],
    [
      "2021-09-03",
      10000.0
    ],
    [
      "2021-09-07",
      10000.0
    ],
    [
      "2021-09-08",
      10000.0
    ],
    [
      "2021-09-09",
      10000.0
    ],
    [
      "2021-09-10",
      10000.0
    ],
    [
      "2021-09-13",
      10000.0
    ],
    [
      "2021-09-14",
      10000.0
    ],
    [
      "2021-09-15",
      10000.0
    ],
    [
      "2021-09-16",
      10000.0
    ],
    [
      "2021-09-17",
      10000.0
    ],
    [
      "2021-09-20",
      10000.0
    ],
    [
      "2021-09-21",
      10000.0
    ],
    [
      "2021-09-22",
      10000.0
    ],
    [
      "2021-09-23",
      10000.0
    ],
    [
      "2021-09-24",
      10000.0
    ],
    [
      "2021-09-27",
      10000.0
    ],
    [
      "2021-09-28",
      10000.0
    ],
    [
      "2021-09-29",
      10000.0
    ],
    [
      "2021-09-30",
      10000.0
    ],
    [
      "2021-10-01",
      10000.0
    ],
    [
      "2021-10-04",
      10000.0
    ],
    [
      "2021-10-05",
      10000.0
    ],
    [
      "2021-10-06",
      10000.0
    ],
    [
      "2021-10-07",
      10000.0
    ],
    [
      "2021-10-08",
      10000.0
    ],
    [
      "2021-10-11",
      10000.0
    ],
    [
      "2021-10-12",
      10000.0
    ],
    [
      "2021-10-13",
      10000.0
    ],
    [
      "2021-10-14",
      10000.0
    ],
    [
      "2021-10-15",
      10000.0
    ],
    [
      "2021-10-18",
      10000.0
    ],
    [
      "2021-10-19",
      10000.0
    ],
    [
      "2021-10-20",
      10000.0
    ],
    [
      "2021-10-21",
      10000.0
    ],
    [
      "2021-10-22",
      10000.0
    ],
    [
      "2021-10-25",
      10000.0
    ],
    [
      "2021-10-26",
      10000.0
    ],
    [
      "2021-10-27",
      10000.0
    ],
    [
      "2021-10-28",
      10000.0
    ],
    [
      "2021-10-29",
      10000.0
    ],
    [
      "2021-11-01",
      10000.0
    ],
    [
      "2021-11-02",
      10000.0
    ],
    [
      "2021-11-03",
      10000.0
    ],
    [
      "2021-11-04",
      10000.0
    ],
    [
      "2021-11-05",
      10000.0
    ],
    [
      "2021-11-08",
      10000.0
    ],
    [
      "2021-11-09",
      10000.0
    ],
    [
      "2021-11-10",
      10000.0
    ],
    [
      "2021-11-11",
      10000.0
    ],
    [
      "2021-11-12",
      10000.0
    ],
    [
      "2021-11-15",
      10006.778270460129
    ],
    [
      "2021-11-16",
      9970.405366636276
    ],
    [
      "2021-11-17",
      9905.894798017502
    ],
    [
      "2021-11-18",
      9988.548293806076
    ],
    [
      "2021-11-19",
      9958.174024320602
    ],
    [
      "2021-11-22",
      9885.422012067795
    ],
    [
      "2021-11-23",
      9946.093927122116
    ],
    [
      "2021-11-24",
      9946.747201658249
    ],
    [
      "2021-11-26",
      9680.733661390304
    ],
    [
      "2021-11-29",
      9799.879995084762
    ],
    [
      "2021-11-30",
      9599.4559762249
    ],
    [
      "2021-12-01",
      9490.277103162765
    ],
    [
      "2021-12-02",
      9667.236299253464
    ],
    [
      "2021-12-03",
      9581.310195661545
    ],
    [
      "2021-12-06",
      9679.05709049797
    ],
    [
      "2021-12-07",
      9880.632051206589
    ],
    [
      "2021-12-08",
      9912.752576566696
    ],
    [
      "2021-12-09",
      9838.856988645553
    ],
    [
      "2021-12-10",
      9879.697801328659
    ],
    [
      "2021-12-13",
      9690.170304990768
    ],
    [
      "2021-12-14",
      9713.973193861008
    ],
    [
      "2021-12-15",
      9833.81518147087
    ],
    [
      "2021-12-16",
      9724.97702763176
    ],
    [
      "2021-12-17",
      9648.458055234909
    ],
    [
      "2021-12-20",
      9561.85310146904
    ],
    [
      "2021-12-21",
      9738.666057325363
    ],
    [
      "2021-12-22",
      9830.193116880417
    ],
    [
      "2021-12-23",
      9897.385598875046
    ],
    [
      "2021-12-27",
      10002.190005994797
    ],
    [
      "2021-12-28",
      9978.449449277878
    ],
    [
      "2021-12-29",
      9996.15806744194
    ],
    [
      "2021-12-30",
      9972.1489865551
    ],
    [
      "2021-12-31",
      9926.82365200615
    ],
    [
      "2022-01-03",
      10019.032726026535
    ],
    [
      "2022-01-04",
      10043.213783002853
    ],
    [
      "2022-01-05",
      9830.284988142013
    ],
    [
      "2022-01-06",
      9914.296107984543
    ],
    [
      "2022-01-07",
      9881.93626186943
    ],
    [
      "2022-01-10",
      9933.706544614792
    ],
    [
      "2022-01-11",
      10012.691905714035
    ],
    [
      "2022-01-12",
      10035.714040494919
    ],
    [
      "2022-01-13",
      9958.465610242843
    ],
    [
      "2022-01-14",
      9946.586007810592
    ],
    [
      "2022-01-18",
      9740.829585767746
    ],
    [
      "2022-01-19",
      9606.337775922775
    ],
    [
      "2022-01-20",
      9484.851464963913
    ],
    [
      "2022-01-21",
      9326.596305585861
    ],
    [
      "2022-01-24",
      9371.980056501388
    ],
    [
      "2022-01-25",
      9323.049173093796
    ],
    [
      "2022-01-26",
      9323.756948209762
    ],
    [
      "2022-01-27",
      9229.587121702194
    ],
    [
      "2022-01-28",
      9420.265283323288
    ],
    [
      "2022-01-31",
      9558.206250883102
    ],
    [
      "2022-02-01",
      9647.013740278244
    ],
    [
      "2022-02-02",
      9735.96712277031
    ],
    [
      "2022-02-03",
      9574.81267140007
    ],
    [
      "2022-02-04",
      9630.917836881637
    ],
    [
      "2022-02-07",
      9635.162290311813
    ],
    [
      "2022-02-08",
      9742.20788738823
    ],
    [
      "2022-02-09",
      9865.736356473923
    ],
    [
      "2022-02-10",
      9772.46343777275
    ],
    [
      "2022-02-11",
      9622.19435474968
    ],
    [
      "2022-02-14",
      9605.501003004074
    ],
    [
      "2022-02-15",
      9601.44768632412
    ],
    [
      "2022-02-16",
      9601.44768632412
    ],
    [
      "2022-02-17",
      9601.44768632412
    ],
    [
      "2022-02-18",
      9601.44768632412
    ],
    [
      "2022-02-22",
      9601.44768632412
    ],
    [
      "2022-02-23",
      9601.44768632412
    ],
    [
      "2022-02-24",
      9601.44768632412
    ],
    [
      "2022-02-25",
      9601.44768632412
    ],
    [
      "2022-02-28",
      9601.44768632412
    ],
    [
      "2022-03-01",
      9601.44768632412
    ],
    [
      "2022-03-02",
      9601.44768632412
    ],
    [
      "2022-03-03",
      9601.44768632412
    ],
    [
      "2022-03-04",
      9601.44768632412
    ],
    [
      "2022-03-07",
      9601.44768632412
    ],
    [
      "2022-03-08",
      9601.44768632412
    ],
    [
      "2022-03-09",
      9601.44768632412
    ],
    [
      "2022-03-10",
      9601.44768632412
    ],
    [
      "2022-03-11",
      9601.44768632412
    ],
    [
      "2022-03-14",
      9601.44768632412
    ],
    [
      "2022-03-15",
      9601.44768632412
    ],
    [
      "2022-03-16",
      9601.44768632412
    ],
    [
      "2022-03-17",
      9601.44768632412
    ],
    [
      "2022-03-18",
      9601.44768632412
    ],
    [
      "2022-03-21",
      9601.44768632412
    ],
    [
      "2022-03-22",
      9601.44768632412
    ],
    [
      "2022-03-23",
      9601.44768632412
    ],
    [
      "2022-03-24",
      9601.44768632412
    ],
    [
      "2022-03-25",
      9601.44768632412
    ],
    [
      "2022-03-28",
      9601.44768632412
    ],
    [
      "2022-03-29",
      9601.44768632412
    ],
    [
      "2022-03-30",
      9601.44768632412
    ],
    [
      "2022-03-31",
      9601.44768632412
    ],
    [
      "2022-04-01",
      9601.44768632412
    ],
    [
      "2022-04-04",
      9601.44768632412
    ],
    [
      "2022-04-05",
      9601.44768632412
    ],
    [
      "2022-04-06",
      9601.44768632412
    ],
    [
      "2022-04-07",
      9601.44768632412
    ],
    [
      "2022-04-08",
      9601.44768632412
    ],
    [
      "2022-04-11",
      9601.44768632412
    ],
    [
      "2022-04-12",
      9601.44768632412
    ],
    [
      "2022-04-13",
      9601.44768632412
    ],
    [
      "2022-04-14",
      9601.44768632412
    ],
    [
      "2022-04-18",
      9601.44768632412
    ],
    [
      "2022-04-19",
      9601.44768632412
    ],
    [
      "2022-04-20",
      9601.44768632412
    ],
    [
      "2022-04-21",
      9601.44768632412
    ],
    [
      "2022-04-22",
      9601.44768632412
    ],
    [
      "2022-04-25",
      9601.44768632412
    ],
    [
      "2022-04-26",
      9601.44768632412
    ],
    [
      "2022-04-27",
      9601.44768632412
    ],
    [
      "2022-04-28",
      9601.44768632412
    ],
    [
      "2022-04-29",
      9601.44768632412
    ],
    [
      "2022-05-02",
      9601.44768632412
    ],
    [
      "2022-05-03",
      9601.44768632412
    ],
    [
      "2022-05-04",
      9601.44768632412
    ],
    [
      "2022-05-05",
      9601.44768632412
    ],
    [
      "2022-05-06",
      9601.44768632412
    ],
    [
      "2022-05-09",
      9601.44768632412
    ],
    [
      "2022-05-10",
      9601.44768632412
    ],
    [
      "2022-05-11",
      9601.44768632412
    ],
    [
      "2022-05-12",
      9601.44768632412
    ]
  ],
  "long_short_enabled": false,
  "exposure_history_sample": []
}